lets/__main__.py
lets/__module__.py
lets/decode/base64.py
lets/encode/base64.py
lets/listen/serve/lets/http.py
lets/sample/mydockermodule.py
lets/sample/mymodule.py
lets/support/autocomplete.py
docker_lets-3.0.7.dist-info/LICENSE
docker_lets-3.0.7.dist-info/METADATA
docker_lets-3.0.7.dist-info/WHEEL
docker_lets-3.0.7.dist-info/entry_points.txt
docker_lets-3.0.7.dist-info/top_level.txt
docker_lets-3.0.7.dist-info/RECORD
