Metadata-Version: 2.1
Name: docker-lets
Version: 3.0.7
Summary: A modular framework for arbitrary action.
Home-page: https://github.com/johneiser/lets
Author: johneiser
License: gpl-3.0
Download-URL: https://github.com/johneiser/lets/releases
Keywords: lets,docker,framework
Platform: UNKNOWN
Classifier: Development Status :: 3 - Alpha
Classifier: Programming Language :: Python :: 3
Classifier: Programming Language :: Python :: 3.5
Classifier: Programming Language :: Python :: 3.6
Classifier: Programming Language :: Python :: 3.7
Requires-Python: >=3.5.0
Requires-Dist: docker
Requires-Dist: flask
Requires-Dist: cryptography
